inox/__init__.py
inox/conftest.py
inox/debug.py
inox/lift.py
inox/numpy.py
inox/random.py
inox/tree.py
inox/nn/__init__.py
inox/nn/activation.py
inox/nn/attention.py
inox/nn/container.py
inox/nn/dropout.py
inox/nn/einops.py
inox/nn/interpolation.py
inox/nn/linear.py
inox/nn/module.py
inox/nn/normalization.py
inox/nn/padding.py
inox/nn/pooling.py
inox/nn/recurrent.py
inox/nn/share.py
inox/nn/ssm.py
inox/nn/state.py
inox-0.8.0.dist-info/licenses/LICENSE
inox-0.8.0.dist-info/METADATA
inox-0.8.0.dist-info/WHEEL
inox-0.8.0.dist-info/top_level.txt
inox-0.8.0.dist-info/RECORD
