Metadata-Version: 2.4
Name: inox
Version: 0.8.0
Summary: Stainless neural networks in JAX
Author-email: François Rozet <francois.rozet@outlook.com>
License-Expression: MIT
Project-URL: documentation, https://inox.readthedocs.io
Project-URL: source, https://github.com/francois-rozet/inox
Project-URL: tracker, https://github.com/francois-rozet/inox/issues
Keywords: jax,pytree,neural networks,deep learning
Classifier: Intended Audience :: Developers
Classifier: Intended Audience :: Science/Research
Classifier: Natural Language :: English
Classifier: Operating System :: OS Independent
Classifier: Programming Language :: Python :: 3
Requires-Python: >=3.9
License-File: LICENSE
Requires-Dist: einops>=0.5.0
Requires-Dist: jax>=0.4.26
Provides-Extra: docs
Requires-Dist: docutils==0.19; extra == "docs"
Requires-Dist: furo==2024.5.6; extra == "docs"
Requires-Dist: myst-nb==1.0.0; extra == "docs"
Requires-Dist: sphinx==7.3.7; extra == "docs"
Provides-Extra: lint
Requires-Dist: pre-commit>=3.7.0; extra == "lint"
Requires-Dist: ruff==0.9.9; extra == "lint"
Provides-Extra: test
Requires-Dist: pytest>=8.0.0; extra == "test"
Dynamic: license-file
